asyncio_sse-0.1.dist-info/RECORD
asyncio_sse-0.1.dist-info/top_level.txt
asyncio_sse-0.1.dist-info/pydist.json
asyncio_sse-0.1.dist-info/WHEEL
asyncio_sse-0.1.dist-info/DESCRIPTION.rst
asyncio_sse-0.1.dist-info/METADATA
sse/exceptions.py
sse/protocol.py
sse/__init__.py
sse/handler.py
sse/server.py
