Metadata-Version: 2.0
Name: asyncio-sse
Version: 0.1
Summary: asyncio Server-Sent Events implementation
Home-page: https://github.com/brutasse/asyncio-sse
Author: Bruno Renié
Author-email: bruno@renie.fr
License: BSD
Platform: UNKNOWN
Classifier: Development Status :: 4 - Beta
Classifier: Environment :: Web Environment
Classifier: Intended Audience :: Developers
Classifier: License :: OSI Approved :: BSD License
Classifier: Programming Language :: Python
Classifier: Programming Language :: Python :: 3.3
Classifier: Programming Language :: Python :: 3.4
Requires-Dist: aiohttp
Requires-Dist: asyncio
